memoryte/__init__.py
memoryte-0.0.1.dev1.dist-info/METADATA
memoryte-0.0.1.dev1.dist-info/WHEEL
memoryte-0.0.1.dev1.dist-info/top_level.txt
memoryte-0.0.1.dev1.dist-info/RECORD
