Metadata-Version: 2.1
Name: memoryte
Version: 0.0.1.dev1
Summary: Bring memory to your LLM applications
Home-page: https://github.com/gusye1234/memoryte
Author: JianbaiYe
Classifier: Programming Language :: Python :: 3
Classifier: License :: OSI Approved :: MIT License
Classifier: Operating System :: OS Independent
Requires-Python: >=3.9
